{"inkVersion":21,"root":[["^Eh?","\n","^Why are you still talking to me?","\n","ev","str","^What am i doing again?","/str","/ev",{"*":"0.c-0","flg":4},"ev","str","^Nevermind...","/str","/ev",{"*":"0.c-1","flg":4},{"c-0":["\n",{"->":"path1"},{"->":"0.g-0"},{"#f":5}],"c-1":["\n","end",{"->":"0.g-0"},{"#f":5}],"g-0":["done",{"#f":5}]}],"done",{"path1":["^There's a heat source over there...","\n","^You can find a recipe book by interacting with it...","\n","^In the book you can find the dish you need to cook!","\n","end",{"#f":1}],"#f":1}],"listDefs":{}}