{"inkVersion":21,"root":[["^Hello there ","#","^speaker: Sugu ","/#","#","^trigger: next","/#","\n",{"->":"main"},["done",{"#f":5,"#n":"g-0"}],null],"done",{"main":[["^Another \"Tourist\" i see? ","#","^speaker: Sugu ","/#","#","^trigger: next","/#","\n","ev","str","^Who are you?","/str","/ev",{"*":".^.c-0","flg":4},"ev","str","^What is this building?","/str","/ev",{"*":".^.c-1","flg":4},"ev","str","^See ya","/str","/ev",{"*":".^.c-2","flg":4},{"c-0":["\n",{"->":"Section1"},{"#f":5}],"c-1":["\n",{"->":"Section2"},{"#f":5}],"c-2":["\n",{"->":"Section3"},{"#f":5}]}],{"#f":1}],"Section1":[["^I should ask you that... ","#","^speaker: Sugu","/#","\n","^But nevermind... Ahem! ","#","^speaker: Sugu","/#","\n","^I am Sugu! Owner of the largest shop in town! ","#","^speaker: Sugu","/#","\n","^We sell a bunch of convenient items for your needs. ","#","^speaker: Sugu","/#","\n","ev","str","^Can I buy something?","/str","/ev",{"*":".^.c-0","flg":4},{"c-0":["\n",{"->":"Section1A"},{"#f":5}]}],{"#f":1}],"Section1A":["^Unfortunately we're still closed.. sorry for the inconvenience. ","#","^speaker: Sugu","/#","\n","end",{"#f":1}],"Section2":["^It's a general store! ","#","^speaker: Sugu","/#","\n","^People come here everyday to shop for daily goods. ","#","^speaker: Sugu","/#","\n","^But we are currently closed during this hour. ","#","^speaker: Sugu","/#","\n","end",{"#f":1}],"Section3":["^Come back next time!","\n","end",{"#f":1}],"#f":1}],"listDefs":{}}